odoo/addons/website_sale_product_minimal_price/README.rst
odoo/addons/website_sale_product_minimal_price/__init__.py
odoo/addons/website_sale_product_minimal_price/__manifest__.py
odoo/addons/website_sale_product_minimal_price/i18n/ca.po
odoo/addons/website_sale_product_minimal_price/i18n/es.po
odoo/addons/website_sale_product_minimal_price/i18n/fr.po
odoo/addons/website_sale_product_minimal_price/i18n/it.po
odoo/addons/website_sale_product_minimal_price/i18n/nl.po
odoo/addons/website_sale_product_minimal_price/i18n/pt.po
odoo/addons/website_sale_product_minimal_price/i18n/website_sale_product_minimal_price.pot
odoo/addons/website_sale_product_minimal_price/models/__init__.py
odoo/addons/website_sale_product_minimal_price/models/product_template.py
odoo/addons/website_sale_product_minimal_price/readme/CONTRIBUTORS.md
odoo/addons/website_sale_product_minimal_price/readme/DESCRIPTION.md
odoo/addons/website_sale_product_minimal_price/readme/USAGE.md
odoo/addons/website_sale_product_minimal_price/static/description/icon.png
odoo/addons/website_sale_product_minimal_price/static/description/index.html
odoo/addons/website_sale_product_minimal_price/static/src/js/website_sale_product_price_scale.esm.js
odoo/addons/website_sale_product_minimal_price/static/src/tests/tours/test_product_with_no_prices_tour.esm.js
odoo/addons/website_sale_product_minimal_price/static/src/tests/tours/tour.esm.js
odoo/addons/website_sale_product_minimal_price/static/src/xml/website_sale_product_price_scale.xml
odoo/addons/website_sale_product_minimal_price/tests/__init__.py
odoo/addons/website_sale_product_minimal_price/tests/test_product_with_no_prices.py
odoo/addons/website_sale_product_minimal_price/tests/test_website_sale_product_minimal_price.py
odoo/addons/website_sale_product_minimal_price/views/templates.xml
odoo_addon_website_sale_product_minimal_price-17.0.1.0.0.3.dist-info/METADATA
odoo_addon_website_sale_product_minimal_price-17.0.1.0.0.3.dist-info/WHEEL
odoo_addon_website_sale_product_minimal_price-17.0.1.0.0.3.dist-info/top_level.txt
odoo_addon_website_sale_product_minimal_price-17.0.1.0.0.3.dist-info/RECORD
